[
    {
        "Class":"NotHate",
        "TotalTokens":696047,
        "UniqueTokens":46258,
        "TTR":0.0665
    },
    {
        "Class":"Racist",
        "TotalTokens":66265,
        "UniqueTokens":10947,
        "TTR":0.1652
    },
    {
        "Class":"Sexist",
        "TotalTokens":23043,
        "UniqueTokens":5436,
        "TTR":0.2359
    },
    {
        "Class":"Homophobe",
        "TotalTokens":20672,
        "UniqueTokens":4849,
        "TTR":0.2346
    },
    {
        "Class":"Religion",
        "TotalTokens":1093,
        "UniqueTokens":624,
        "TTR":0.5709
    },
    {
        "Class":"OtherHate",
        "TotalTokens":30827,
        "UniqueTokens":7258,
        "TTR":0.2354
    }
]